<?xml version="1.0" encoding="UTF-8"?>
<!DOCTYPE score-partwise PUBLIC "-//Recordare//DTD MusicXML 3.0 Partwise//EN" "http://www.musicxml.org/dtds/partwise.dtd">
<score-partwise>
  <identification>
    <encoding>
      <software>MuseScore 2.0.3</software>
      <encoding-date>2016-04-22</encoding-date>
      <supports element="accidental" type="yes"/>
      <supports element="beam" type="yes"/>
      <supports element="print" attribute="new-page" type="yes" value="yes"/>
      <supports element="print" attribute="new-system" type="yes" value="yes"/>
      <supports element="stem" type="yes"/>
      </encoding>
    </identification>
  <defaults>
    <scaling>
      <millimeters>7.05556</millimeters>
      <tenths>40</tenths>
      </scaling>
    <page-layout>
      <page-height>1683.78</page-height>
      <page-width>1190.55</page-width>
      <page-margins type="even">
        <left-margin>56.6929</left-margin>
        <right-margin>56.6929</right-margin>
        <top-margin>56.6929</top-margin>
        <bottom-margin>113.386</bottom-margin>
        </page-margins>
      <page-margins type="odd">
        <left-margin>56.6929</left-margin>
        <right-margin>56.6929</right-margin>
        <top-margin>56.6929</top-margin>
        <bottom-margin>113.386</bottom-margin>
        </page-margins>
      </page-layout>
    <word-font font-family="FreeSerif" font-size="10"/>
    <lyric-font font-family="FreeSerif" font-size="11"/>
    </defaults>
  <part-list>
    <score-part id="P1">
      <part-name>Piano, Melody</part-name>
      <part-abbreviation>Pno.</part-abbreviation>
      <score-instrument id="P1-I1">
        <instrument-name>Piano</instrument-name>
        </score-instrument>
      <midi-device id="P1-I1" port="1"></midi-device>
      <midi-instrument id="P1-I1">
        <midi-channel>1</midi-channel>
        <midi-program>1</midi-program>
        <volume>78.7402</volume>
        <pan>0</pan>
        </midi-instrument>
      </score-part>
    </part-list>
  <part id="P1">
    <measure number="1" width="527.82">
      <print>
        <system-layout>
          <system-margins>
            <left-margin>0.00</left-margin>
            <right-margin>0.00</right-margin>
            </system-margins>
          <top-system-distance>70.00</top-system-distance>
          </system-layout>
        </print>
      <attributes>
        <divisions>12</divisions>
        <key>
          <fifths>-6</fifths>
          </key>
        <time>
          <beats>9</beats>
          <beat-type>4</beat-type>
          </time>
        <clef>
          <sign>G</sign>
          <line>2</line>
          </clef>
        </attributes>
      <direction placement="above">
        <direction-type>
          <metronome parentheses="no">
            <beat-unit>quarter</beat-unit>
            <per-minute>194</per-minute>
            </metronome>
          </direction-type>
        <sound tempo="194"/>
        </direction>
      <note default-x="136.63" default-y="-30.00" dynamics="111.11">
        <pitch>
          <step>G</step>
          <octave>4</octave>
          </pitch>
        <duration>6</duration>
        <voice>1</voice>
        <type>eighth</type>
        <accidental>natural</accidental>
        <stem>down</stem>
        <beam number="1">begin</beam>
        </note>
      <note default-x="172.02" default-y="-20.00" dynamics="111.11">
        <pitch>
          <step>B</step>
          <alter>-2</alter>
          <octave>4</octave>
          </pitch>
        <duration>6</duration>
        <voice>1</voice>
        <type>eighth</type>
        <accidental>flat-flat</accidental>
        <stem>down</stem>
        <beam number="1">continue</beam>
        </note>
      <note default-x="198.04" default-y="-15.00" dynamics="111.11">
        <pitch>
          <step>C</step>
          <alter>-1</alter>
          <octave>5</octave>
          </pitch>
        <duration>6</duration>
        <voice>1</voice>
        <type>eighth</type>
        <stem>down</stem>
        <beam number="1">continue</beam>
        </note>
      <note default-x="224.06" default-y="-10.00" dynamics="111.11">
        <pitch>
          <step>D</step>
          <alter>-1</alter>
          <octave>5</octave>
          </pitch>
        <duration>6</duration>
        <voice>1</voice>
        <type>eighth</type>
        <stem>down</stem>
        <beam number="1">continue</beam>
        </note>
      <note default-x="250.09" default-y="-20.00" dynamics="111.11">
        <pitch>
          <step>B</step>
          <alter>-2</alter>
          <octave>4</octave>
          </pitch>
        <duration>6</duration>
        <voice>1</voice>
        <type>eighth</type>
        <stem>down</stem>
        <beam number="1">continue</beam>
        </note>
      <note default-x="276.11" default-y="-30.00" dynamics="111.11">
        <pitch>
          <step>G</step>
          <octave>4</octave>
          </pitch>
        <duration>3</duration>
        <voice>1</voice>
        <type>16th</type>
        <stem>down</stem>
        <beam number="1">continue</beam>
        <beam number="2">begin</beam>
        </note>
      <note default-x="292.37" default-y="-15.00" dynamics="111.11">
        <pitch>
          <step>C</step>
          <alter>-1</alter>
          <octave>5</octave>
          </pitch>
        <duration>3</duration>
        <voice>1</voice>
        <type>16th</type>
        <stem>down</stem>
        <beam number="1">continue</beam>
        <beam number="2">end</beam>
        </note>
      <note default-x="321.30" default-y="0.00" dynamics="111.11">
        <pitch>
          <step>F</step>
          <alter>-1</alter>
          <octave>5</octave>
          </pitch>
        <duration>6</duration>
        <voice>1</voice>
        <type>eighth</type>
        <accidental>flat</accidental>
        <stem>down</stem>
        <beam number="1">continue</beam>
        </note>
      <note default-x="347.32" default-y="5.00" dynamics="111.11">
        <pitch>
          <step>G</step>
          <alter>-1</alter>
          <octave>5</octave>
          </pitch>
        <duration>6</duration>
        <voice>1</voice>
        <type>eighth</type>
        <stem>down</stem>
        <beam number="1">end</beam>
        </note>
      <note default-x="373.35" default-y="0.00" dynamics="111.11">
        <pitch>
          <step>F</step>
          <alter>-1</alter>
          <octave>5</octave>
          </pitch>
        <duration>12</duration>
        <voice>1</voice>
        <type>quarter</type>
        <stem>down</stem>
        <notations>
          <articulations>
            <staccato/>
            </articulations>
          </notations>
        </note>
      <note default-x="409.13" default-y="-10.00" dynamics="111.11">
        <pitch>
          <step>D</step>
          <alter>-1</alter>
          <octave>5</octave>
          </pitch>
        <duration>12</duration>
        <tie type="start"/>
        <voice>1</voice>
        <type>quarter</type>
        <stem>down</stem>
        <notations>
          <tied type="start"/>
          </notations>
        </note>
      <note default-x="444.90" default-y="-10.00" dynamics="111.11">
        <pitch>
          <step>D</step>
          <alter>-1</alter>
          <octave>5</octave>
          </pitch>
        <duration>12</duration>
        <tie type="stop"/>
        <voice>1</voice>
        <type>quarter</type>
        <stem>down</stem>
        <notations>
          <tied type="stop"/>
          </notations>
        </note>
      <note default-x="480.32" default-y="-15.00" dynamics="111.11">
        <pitch>
          <step>C</step>
          <octave>5</octave>
          </pitch>
        <duration>24</duration>
        <voice>1</voice>
        <type>half</type>
        <accidental>natural</accidental>
        <stem>down</stem>
        <notations>
          <articulations>
            <staccato/>
            </articulations>
          </notations>
        </note>
      </measure>
    <measure number="2" width="549.35">
      <note>
        <rest/>
        <duration>36</duration>
        <voice>1</voice>
        <type>half</type>
        <dot/>
        </note>
      <note>
        <rest/>
        <duration>12</duration>
        <voice>1</voice>
        <type>quarter</type>
        </note>
      <note>
        <rest/>
        <duration>12</duration>
        <voice>1</voice>
        <type>quarter</type>
        </note>
      <note>
        <rest/>
        <duration>6</duration>
        <voice>1</voice>
        <type>eighth</type>
        </note>
      <note default-x="380.83" default-y="0.00" dynamics="111.11">
        <pitch>
          <step>F</step>
          <alter>-1</alter>
          <octave>5</octave>
          </pitch>
        <duration>6</duration>
        <tie type="start"/>
        <voice>1</voice>
        <type>eighth</type>
        <accidental>flat</accidental>
        <stem>up</stem>
        <notations>
          <tied type="start"/>
          </notations>
        </note>
      <note default-x="419.37" default-y="0.00" dynamics="111.11">
        <pitch>
          <step>F</step>
          <alter>-1</alter>
          <octave>5</octave>
          </pitch>
        <duration>36</duration>
        <tie type="stop"/>
        <voice>1</voice>
        <type>half</type>
        <dot/>
        <stem>up</stem>
        <notations>
          <tied type="stop"/>
          </notations>
        </note>
      <backup>
        <duration>108</duration>
        </backup>
      <note>
        <rest/>
        <duration>12</duration>
        <voice>2</voice>
        <type>quarter</type>
        </note>
      <note>
        <rest/>
        <duration>6</duration>
        <voice>2</voice>
        <type>eighth</type>
        </note>
      <note>
        <rest/>
        <duration>3</duration>
        <voice>2</voice>
        <type>16th</type>
        </note>
      <note default-x="117.44" default-y="-50.00" dynamics="111.11">
        <pitch>
          <step>C</step>
          <octave>4</octave>
          </pitch>
        <duration>3</duration>
        <voice>2</voice>
        <type>16th</type>
        <accidental>natural</accidental>
        <stem>down</stem>
        <beam number="1">begin</beam>
        <beam number="2">forward hook</beam>
        </note>
      <note default-x="144.46" default-y="-45.00" dynamics="111.11">
        <pitch>
          <step>D</step>
          <octave>4</octave>
          </pitch>
        <duration>4</duration>
        <voice>2</voice>
        <type>eighth</type>
        <accidental>natural</accidental>
        <time-modification>
          <actual-notes>3</actual-notes>
          <normal-notes>2</normal-notes>
          </time-modification>
        <stem>down</stem>
        <beam number="1">continue</beam>
        <notations>
          <tuplet type="start" bracket="no"/>
          </notations>
        </note>
      <note default-x="169.64" default-y="-35.00" dynamics="111.11">
        <pitch>
          <step>F</step>
          <octave>4</octave>
          </pitch>
        <duration>4</duration>
        <voice>2</voice>
        <type>eighth</type>
        <time-modification>
          <actual-notes>3</actual-notes>
          <normal-notes>2</normal-notes>
          </time-modification>
        <stem>down</stem>
        <beam number="1">continue</beam>
        </note>
      <note default-x="196.66" default-y="-30.00" dynamics="111.11">
        <pitch>
          <step>G</step>
          <octave>4</octave>
          </pitch>
        <duration>4</duration>
        <voice>2</voice>
        <type>eighth</type>
        <accidental>natural</accidental>
        <time-modification>
          <actual-notes>3</actual-notes>
          <normal-notes>2</normal-notes>
          </time-modification>
        <stem>down</stem>
        <beam number="1">continue</beam>
        <notations>
          <tuplet type="stop"/>
          </notations>
        </note>
      <note default-x="221.84" default-y="-20.00" dynamics="111.11">
        <pitch>
          <step>B</step>
          <alter>-1</alter>
          <octave>4</octave>
          </pitch>
        <duration>4</duration>
        <voice>2</voice>
        <type>eighth</type>
        <time-modification>
          <actual-notes>3</actual-notes>
          <normal-notes>2</normal-notes>
          <normal-type>eighth</normal-type>
          </time-modification>
        <stem>down</stem>
        <beam number="1">end</beam>
        <notations>
          <tuplet type="start" bracket="yes"/>
          </notations>
        </note>
      <note default-x="248.86" default-y="-15.00" dynamics="111.11">
        <pitch>
          <step>C</step>
          <octave>5</octave>
          </pitch>
        <duration>8</duration>
        <voice>2</voice>
        <type>quarter</type>
        <accidental>natural</accidental>
        <time-modification>
          <actual-notes>3</actual-notes>
          <normal-notes>2</normal-notes>
          <normal-type>eighth</normal-type>
          </time-modification>
        <stem>down</stem>
        <notations>
          <tuplet type="stop"/>
          </notations>
        </note>
      <note default-x="286.13" default-y="-10.00" dynamics="111.11">
        <pitch>
          <step>D</step>
          <octave>5</octave>
          </pitch>
        <duration>4</duration>
        <voice>2</voice>
        <type>eighth</type>
        <accidental>natural</accidental>
        <time-modification>
          <actual-notes>3</actual-notes>
          <normal-notes>2</normal-notes>
          <normal-type>eighth</normal-type>
          </time-modification>
        <stem>down</stem>
        <notations>
          <tuplet type="start" bracket="yes"/>
          </notations>
        </note>
      <note default-x="311.30" default-y="0.00" dynamics="111.11">
        <pitch>
          <step>F</step>
          <octave>5</octave>
          </pitch>
        <duration>8</duration>
        <voice>2</voice>
        <type>quarter</type>
        <time-modification>
          <actual-notes>3</actual-notes>
          <normal-notes>2</normal-notes>
          <normal-type>eighth</normal-type>
          </time-modification>
        <stem>down</stem>
        <notations>
          <tuplet type="stop"/>
          </notations>
        </note>
      <note default-x="348.57" default-y="5.00" dynamics="111.11">
        <pitch>
          <step>G</step>
          <alter>-1</alter>
          <octave>5</octave>
          </pitch>
        <duration>12</duration>
        <voice>2</voice>
        <type>quarter</type>
        <stem>down</stem>
        <notations>
          <articulations>
            <staccato/>
            </articulations>
          </notations>
        </note>
      <note default-x="419.73" default-y="-10.00" dynamics="111.11">
        <pitch>
          <step>D</step>
          <alter>-1</alter>
          <octave>5</octave>
          </pitch>
        <duration>18</duration>
        <voice>2</voice>
        <type>quarter</type>
        <dot/>
        <accidental>flat</accidental>
        <stem>down</stem>
        </note>
      <note default-x="471.15" default-y="-15.00" dynamics="111.11">
        <pitch>
          <step>C</step>
          <alter>-1</alter>
          <octave>5</octave>
          </pitch>
        <duration>6</duration>
        <voice>2</voice>
        <type>eighth</type>
        <accidental>flat</accidental>
        <stem>down</stem>
        </note>
      <note default-x="503.40" default-y="-15.00" dynamics="111.11">
        <pitch>
          <step>C</step>
          <octave>5</octave>
          </pitch>
        <duration>12</duration>
        <tie type="start"/>
        <voice>2</voice>
        <type>quarter</type>
        <accidental>natural</accidental>
        <stem>down</stem>
        <notations>
          <tied type="start"/>
          </notations>
        </note>
      </measure>
    <measure number="3" width="1077.17">
      <print new-system="yes">
        <system-layout>
          <system-margins>
            <left-margin>0.00</left-margin>
            <right-margin>0.00</right-margin>
            </system-margins>
          <system-distance>150.00</system-distance>
          </system-layout>
        </print>
      <note>
        <rest/>
        <duration>108</duration>
        <voice>1</voice>
        </note>
      <backup>
        <duration>108</duration>
        </backup>
      <note default-x="115.68" default-y="-15.00" dynamics="111.11">
        <pitch>
          <step>C</step>
          <octave>5</octave>
          </pitch>
        <duration>6</duration>
        <tie type="stop"/>
        <voice>2</voice>
        <type>eighth</type>
        <stem>down</stem>
        <beam number="1">begin</beam>
        <notations>
          <tied type="stop"/>
          </notations>
        </note>
      <note default-x="185.55" default-y="-20.00" dynamics="111.11">
        <pitch>
          <step>B</step>
          <alter>-1</alter>
          <octave>4</octave>
          </pitch>
        <duration>6</duration>
        <voice>2</voice>
        <type>eighth</type>
        <stem>down</stem>
        <beam number="1">continue</beam>
        </note>
      <note default-x="255.43" default-y="-30.00" dynamics="111.11">
        <pitch>
          <step>G</step>
          <octave>4</octave>
          </pitch>
        <duration>4</duration>
        <voice>2</voice>
        <type>eighth</type>
        <accidental>natural</accidental>
        <time-modification>
          <actual-notes>3</actual-notes>
          <normal-notes>2</normal-notes>
          <normal-type>eighth</normal-type>
          </time-modification>
        <stem>down</stem>
        <beam number="1">end</beam>
        <notations>
          <tuplet type="start" bracket="yes"/>
          </notations>
        </note>
      <note default-x="307.15" default-y="-40.00" dynamics="111.11">
        <pitch>
          <step>E</step>
          <alter>-1</alter>
          <octave>4</octave>
          </pitch>
        <duration>8</duration>
        <voice>2</voice>
        <type>quarter</type>
        <time-modification>
          <actual-notes>3</actual-notes>
          <normal-notes>2</normal-notes>
          <normal-type>eighth</normal-type>
          </time-modification>
        <stem>down</stem>
        <notations>
          <tuplet type="stop"/>
          </notations>
        </note>
      <note default-x="389.90" default-y="-20.00" dynamics="111.11">
        <pitch>
          <step>B</step>
          <alter>-2</alter>
          <octave>4</octave>
          </pitch>
        <duration>12</duration>
        <voice>2</voice>
        <type>quarter</type>
        <accidental>flat-flat</accidental>
        <stem>down</stem>
        <notations>
          <articulations>
            <staccato/>
            </articulations>
          </notations>
        </note>
      <note default-x="490.45" default-y="-15.00" dynamics="111.11">
        <pitch>
          <step>C</step>
          <alter>-1</alter>
          <octave>5</octave>
          </pitch>
        <duration>36</duration>
        <voice>2</voice>
        <type>half</type>
        <dot/>
        <accidental>flat</accidental>
        <stem>down</stem>
        <notations>
          <articulations>
            <staccato/>
            </articulations>
          </notations>
        </note>
      <note default-x="640.90" default-y="-30.00" dynamics="111.11">
        <pitch>
          <step>G</step>
          <alter>-1</alter>
          <octave>4</octave>
          </pitch>
        <duration>4</duration>
        <voice>2</voice>
        <type>eighth</type>
        <accidental>flat</accidental>
        <time-modification>
          <actual-notes>3</actual-notes>
          <normal-notes>2</normal-notes>
          </time-modification>
        <stem>down</stem>
        <beam number="1">begin</beam>
        <notations>
          <tuplet type="start" bracket="no"/>
          </notations>
        </note>
      <note default-x="692.62" default-y="-20.00" dynamics="111.11">
        <pitch>
          <step>B</step>
          <alter>-2</alter>
          <octave>4</octave>
          </pitch>
        <duration>4</duration>
        <voice>2</voice>
        <type>eighth</type>
        <time-modification>
          <actual-notes>3</actual-notes>
          <normal-notes>2</normal-notes>
          </time-modification>
        <stem>down</stem>
        <beam number="1">continue</beam>
        </note>
      <note default-x="744.35" default-y="-35.00" dynamics="111.11">
        <pitch>
          <step>F</step>
          <alter>-1</alter>
          <octave>4</octave>
          </pitch>
        <duration>4</duration>
        <voice>2</voice>
        <type>eighth</type>
        <accidental>flat</accidental>
        <time-modification>
          <actual-notes>3</actual-notes>
          <normal-notes>2</normal-notes>
          </time-modification>
        <stem>down</stem>
        <beam number="1">continue</beam>
        <notations>
          <tuplet type="stop"/>
          </notations>
        </note>
      <note default-x="796.07" default-y="-50.00" dynamics="111.11">
        <pitch>
          <step>C</step>
          <alter>-1</alter>
          <octave>4</octave>
          </pitch>
        <duration>6</duration>
        <voice>2</voice>
        <type>eighth</type>
        <stem>down</stem>
        <beam number="1">continue</beam>
        </note>
      <note default-x="865.94" default-y="-45.00" dynamics="111.11">
        <pitch>
          <step>D</step>
          <alter>-1</alter>
          <octave>4</octave>
          </pitch>
        <duration>6</duration>
        <voice>2</voice>
        <type>eighth</type>
        <stem>down</stem>
        <beam number="1">continue</beam>
        </note>
      <note default-x="935.82" default-y="-30.00" dynamics="111.11">
        <pitch>
          <step>G</step>
          <alter>-1</alter>
          <octave>4</octave>
          </pitch>
        <duration>6</duration>
        <voice>2</voice>
        <type>eighth</type>
        <stem>down</stem>
        <beam number="1">continue</beam>
        </note>
      <note default-x="1005.69" default-y="-40.00" dynamics="111.11">
        <pitch>
          <step>E</step>
          <alter>-1</alter>
          <octave>4</octave>
          </pitch>
        <duration>6</duration>
        <tie type="start"/>
        <voice>2</voice>
        <type>eighth</type>
        <stem>down</stem>
        <beam number="1">end</beam>
        <notations>
          <tied type="start"/>
          </notations>
        </note>
      </measure>
    <measure number="4" width="1077.17">
      <print new-system="yes">
        <system-layout>
          <system-margins>
            <left-margin>0.00</left-margin>
            <right-margin>0.00</right-margin>
            </system-margins>
          <system-distance>150.00</system-distance>
          </system-layout>
        </print>
      <note>
        <rest/>
        <duration>36</duration>
        <voice>1</voice>
        <type>half</type>
        <dot/>
        </note>
      <note>
        <rest/>
        <duration>6</duration>
        <voice>1</voice>
        <type>eighth</type>
        </note>
      <note default-x="459.80" default-y="-35.00" dynamics="111.11">
        <pitch>
          <step>F</step>
          <octave>4</octave>
          </pitch>
        <duration>6</duration>
        <tie type="start"/>
        <voice>1</voice>
        <type>eighth</type>
        <stem>up</stem>
        <notations>
          <tied type="start"/>
          </notations>
        </note>
      <note default-x="511.16" default-y="-35.00" dynamics="111.11">
        <pitch>
          <step>F</step>
          <octave>4</octave>
          </pitch>
        <duration>24</duration>
        <tie type="stop"/>
        <voice>1</voice>
        <type>half</type>
        <stem>up</stem>
        <notations>
          <tied type="stop"/>
          </notations>
        </note>
      <note>
        <rest/>
        <duration>36</duration>
        <voice>1</voice>
        <type>half</type>
        <dot/>
        </note>
      <backup>
        <duration>108</duration>
        </backup>
      <note default-x="115.68" default-y="-40.00" dynamics="111.11">
        <pitch>
          <step>E</step>
          <alter>-1</alter>
          <octave>4</octave>
          </pitch>
        <duration>12</duration>
        <tie type="stop"/>
        <voice>2</voice>
        <type>quarter</type>
        <stem>down</stem>
        <notations>
          <tied type="stop"/>
          </notations>
        </note>
      <note default-x="186.80" default-y="-25.00" dynamics="111.11">
        <pitch>
          <step>A</step>
          <alter>-1</alter>
          <octave>4</octave>
          </pitch>
        <duration>8</duration>
        <voice>2</voice>
        <type>quarter</type>
        <time-modification>
          <actual-notes>3</actual-notes>
          <normal-notes>2</normal-notes>
          <normal-type>eighth</normal-type>
          </time-modification>
        <stem>down</stem>
        <notations>
          <tuplet type="start" bracket="yes"/>
          </notations>
        </note>
      <note default-x="246.57" default-y="-40.00" dynamics="111.11">
        <pitch>
          <step>E</step>
          <alter>-1</alter>
          <octave>4</octave>
          </pitch>
        <duration>4</duration>
        <voice>2</voice>
        <type>eighth</type>
        <time-modification>
          <actual-notes>3</actual-notes>
          <normal-notes>2</normal-notes>
          <normal-type>eighth</normal-type>
          </time-modification>
        <stem>down</stem>
        <beam number="1">begin</beam>
        <notations>
          <tuplet type="stop"/>
          </notations>
        </note>
      <note default-x="286.95" default-y="-45.00" dynamics="111.11">
        <pitch>
          <step>D</step>
          <alter>-1</alter>
          <octave>4</octave>
          </pitch>
        <duration>4</duration>
        <voice>2</voice>
        <type>eighth</type>
        <time-modification>
          <actual-notes>3</actual-notes>
          <normal-notes>2</normal-notes>
          </time-modification>
        <stem>down</stem>
        <beam number="1">continue</beam>
        <notations>
          <tuplet type="start" bracket="no"/>
          </notations>
        </note>
      <note default-x="327.32" default-y="-30.00" dynamics="111.11">
        <pitch>
          <step>G</step>
          <alter>-1</alter>
          <octave>4</octave>
          </pitch>
        <duration>4</duration>
        <voice>2</voice>
        <type>eighth</type>
        <time-modification>
          <actual-notes>3</actual-notes>
          <normal-notes>2</normal-notes>
          </time-modification>
        <stem>down</stem>
        <beam number="1">continue</beam>
        </note>
      <note default-x="367.70" default-y="-25.00" dynamics="111.11">
        <pitch>
          <step>A</step>
          <alter>-1</alter>
          <octave>4</octave>
          </pitch>
        <duration>4</duration>
        <voice>2</voice>
        <type>eighth</type>
        <time-modification>
          <actual-notes>3</actual-notes>
          <normal-notes>2</normal-notes>
          </time-modification>
        <stem>down</stem>
        <beam number="1">end</beam>
        <notations>
          <tuplet type="stop"/>
          </notations>
        </note>
      <note default-x="408.08" default-y="-30.00" dynamics="111.11">
        <pitch>
          <step>G</step>
          <octave>4</octave>
          </pitch>
        <duration>12</duration>
        <voice>2</voice>
        <type>quarter</type>
        <accidental>natural</accidental>
        <stem>down</stem>
        <notations>
          <articulations>
            <staccato/>
            </articulations>
          </notations>
        </note>
      <note>
        <rest/>
        <duration>3</duration>
        <voice>2</voice>
        <type>16th</type>
        </note>
      <note default-x="543.85" default-y="-20.00" dynamics="111.11">
        <pitch>
          <step>B</step>
          <alter>-1</alter>
          <octave>4</octave>
          </pitch>
        <duration>3</duration>
        <tie type="start"/>
        <voice>2</voice>
        <type>16th</type>
        <stem>down</stem>
        <beam number="1">begin</beam>
        <beam number="2">forward hook</beam>
        <notations>
          <tied type="start"/>
          <articulations>
            <staccato/>
            </articulations>
          </notations>
        </note>
      <note default-x="570.87" default-y="-20.00" dynamics="111.11">
        <pitch>
          <step>B</step>
          <alter>-1</alter>
          <octave>4</octave>
          </pitch>
        <duration>6</duration>
        <tie type="stop"/>
        <voice>2</voice>
        <type>eighth</type>
        <stem>down</stem>
        <beam number="1">continue</beam>
        <notations>
          <tied type="stop"/>
          <articulations>
            <staccato/>
            </articulations>
          </notations>
        </note>
      <note default-x="582.74" default-y="-15.00" dynamics="111.11">
        <chord/>
        <pitch>
          <step>C</step>
          <octave>5</octave>
          </pitch>
        <duration>6</duration>
        <tie type="start"/>
        <voice>2</voice>
        <type>eighth</type>
        <accidental>natural</accidental>
        <stem>down</stem>
        <notations>
          <tied type="start"/>
          </notations>
        </note>
      <note default-x="634.46" default-y="-15.00" dynamics="111.11">
        <pitch>
          <step>C</step>
          <octave>5</octave>
          </pitch>
        <duration>6</duration>
        <tie type="stop"/>
        <voice>2</voice>
        <type>eighth</type>
        <stem>down</stem>
        <beam number="1">continue</beam>
        <notations>
          <tied type="stop"/>
          </notations>
        </note>
      <note default-x="686.18" default-y="-30.00" dynamics="111.11">
        <pitch>
          <step>G</step>
          <octave>4</octave>
          </pitch>
        <duration>6</duration>
        <voice>2</voice>
        <type>eighth</type>
        <stem>down</stem>
        <beam number="1">continue</beam>
        </note>
      <note default-x="737.91" default-y="-20.00" dynamics="111.11">
        <pitch>
          <step>B</step>
          <alter>-1</alter>
          <octave>4</octave>
          </pitch>
        <duration>4</duration>
        <voice>2</voice>
        <type>eighth</type>
        <time-modification>
          <actual-notes>3</actual-notes>
          <normal-notes>2</normal-notes>
          </time-modification>
        <stem>down</stem>
        <beam number="1">continue</beam>
        <notations>
          <tuplet type="start" bracket="no"/>
          </notations>
        </note>
      <note default-x="778.28" default-y="-15.00" dynamics="111.11">
        <pitch>
          <step>C</step>
          <alter>-1</alter>
          <octave>5</octave>
          </pitch>
        <duration>4</duration>
        <voice>2</voice>
        <type>eighth</type>
        <accidental>flat</accidental>
        <time-modification>
          <actual-notes>3</actual-notes>
          <normal-notes>2</normal-notes>
          </time-modification>
        <stem>down</stem>
        <beam number="1">continue</beam>
        </note>
      <note default-x="818.66" default-y="-20.00" dynamics="111.11">
        <pitch>
          <step>B</step>
          <alter>-1</alter>
          <octave>4</octave>
          </pitch>
        <duration>4</duration>
        <voice>2</voice>
        <type>eighth</type>
        <time-modification>
          <actual-notes>3</actual-notes>
          <normal-notes>2</normal-notes>
          </time-modification>
        <stem>down</stem>
        <beam number="1">end</beam>
        <notations>
          <tuplet type="stop"/>
          </notations>
        </note>
      <note default-x="859.04" default-y="-20.00" dynamics="111.11">
        <pitch>
          <step>B</step>
          <alter>-2</alter>
          <octave>4</octave>
          </pitch>
        <duration>8</duration>
        <voice>2</voice>
        <type>quarter</type>
        <accidental>flat-flat</accidental>
        <time-modification>
          <actual-notes>3</actual-notes>
          <normal-notes>2</normal-notes>
          <normal-type>eighth</normal-type>
          </time-modification>
        <stem>down</stem>
        <notations>
          <tuplet type="start" bracket="yes"/>
          </notations>
        </note>
      <note default-x="918.81" default-y="-30.00" dynamics="111.11">
        <pitch>
          <step>G</step>
          <alter>-1</alter>
          <octave>4</octave>
          </pitch>
        <duration>4</duration>
        <voice>2</voice>
        <type>eighth</type>
        <accidental>flat</accidental>
        <time-modification>
          <actual-notes>3</actual-notes>
          <normal-notes>2</normal-notes>
          <normal-type>eighth</normal-type>
          </time-modification>
        <stem>down</stem>
        <beam number="1">begin</beam>
        <notations>
          <tuplet type="stop"/>
          </notations>
        </note>
      <note default-x="959.19" default-y="-35.00" dynamics="111.11">
        <pitch>
          <step>F</step>
          <alter>-1</alter>
          <octave>4</octave>
          </pitch>
        <duration>6</duration>
        <voice>2</voice>
        <type>eighth</type>
        <accidental>flat</accidental>
        <stem>down</stem>
        <beam number="1">continue</beam>
        <notations>
          <articulations>
            <staccato/>
            </articulations>
          </notations>
        </note>
      <note default-x="1010.91" default-y="-50.00" dynamics="111.11">
        <pitch>
          <step>C</step>
          <alter>-1</alter>
          <octave>4</octave>
          </pitch>
        <duration>3</duration>
        <voice>2</voice>
        <type>16th</type>
        <stem>down</stem>
        <beam number="1">continue</beam>
        <beam number="2">begin</beam>
        </note>
      <note default-x="1043.24" default-y="-30.00" dynamics="111.11">
        <pitch>
          <step>G</step>
          <alter>-1</alter>
          <octave>4</octave>
          </pitch>
        <duration>3</duration>
        <tie type="start"/>
        <voice>2</voice>
        <type>16th</type>
        <stem>down</stem>
        <beam number="1">end</beam>
        <beam number="2">end</beam>
        <notations>
          <tied type="start"/>
          </notations>
        </note>
      </measure>
    <measure number="5" width="734.80">
      <print new-system="yes">
        <system-layout>
          <system-margins>
            <left-margin>0.00</left-margin>
            <right-margin>0.00</right-margin>
            </system-margins>
          <system-distance>150.00</system-distance>
          </system-layout>
        </print>
      <note>
        <rest/>
        <duration>3</duration>
        <voice>1</voice>
        <type>16th</type>
        </note>
      <note default-x="152.07" default-y="-20.00" dynamics="111.11">
        <pitch>
          <step>B</step>
          <alter>-2</alter>
          <octave>4</octave>
          </pitch>
        <duration>9</duration>
        <tie type="start"/>
        <voice>1</voice>
        <type>eighth</type>
        <dot/>
        <accidental>flat-flat</accidental>
        <stem>up</stem>
        <notations>
          <tied type="start"/>
          <articulations>
            <staccato/>
            </articulations>
          </notations>
        </note>
      <note default-x="220.82" default-y="-20.00" dynamics="111.11">
        <pitch>
          <step>B</step>
          <alter>-2</alter>
          <octave>4</octave>
          </pitch>
        <duration>24</duration>
        <tie type="stop"/>
        <voice>1</voice>
        <type>half</type>
        <stem>up</stem>
        <notations>
          <tied type="stop"/>
          </notations>
        </note>
      <note>
        <rest/>
        <duration>36</duration>
        <voice>1</voice>
        <type>half</type>
        <dot/>
        </note>
      <backup>
        <duration>12</duration>
        </backup>
      <attributes>
        <clef>
          <sign>F</sign>
          <line>4</line>
          </clef>
        </attributes>
      <forward>
        <duration>12</duration>
        </forward>
      <note>
        <rest/>
        <duration>36</duration>
        <voice>1</voice>
        <type>half</type>
        <dot/>
        </note>
      <backup>
        <duration>8</duration>
        </backup>
      <attributes>
        <clef>
          <sign>G</sign>
          <line>2</line>
          </clef>
        </attributes>
      <forward>
        <duration>8</duration>
        </forward>
      <backup>
        <duration>108</duration>
        </backup>
      <note default-x="116.68" default-y="-30.00" dynamics="111.11">
        <pitch>
          <step>G</step>
          <alter>-1</alter>
          <octave>4</octave>
          </pitch>
        <duration>6</duration>
        <tie type="stop"/>
        <voice>2</voice>
        <type>eighth</type>
        <stem>down</stem>
        <beam number="1">begin</beam>
        <notations>
          <tied type="stop"/>
          </notations>
        </note>
      <note default-x="188.70" default-y="-30.00" dynamics="111.11">
        <pitch>
          <step>G</step>
          <octave>4</octave>
          </pitch>
        <duration>6</duration>
        <voice>2</voice>
        <type>eighth</type>
        <accidental>natural</accidental>
        <stem>down</stem>
        <beam number="1">end</beam>
        </note>
      <note default-x="220.82" default-y="-40.00" dynamics="111.11">
        <pitch>
          <step>E</step>
          <alter>-1</alter>
          <octave>4</octave>
          </pitch>
        <duration>24</duration>
        <voice>2</voice>
        <type>half</type>
        <stem>down</stem>
        <notations>
          <articulations>
            <staccato/>
            </articulations>
          </notations>
        </note>
      <note default-x="278.02" default-y="-30.00" dynamics="111.11">
        <pitch>
          <step>G</step>
          <octave>4</octave>
          </pitch>
        <duration>6</duration>
        <voice>2</voice>
        <type>eighth</type>
        <stem>down</stem>
        <beam number="1">begin</beam>
        </note>
      <note default-x="310.50" default-y="-35.00" dynamics="111.11">
        <pitch>
          <step>F</step>
          <octave>4</octave>
          </pitch>
        <duration>3</duration>
        <voice>2</voice>
        <type>16th</type>
        <stem>down</stem>
        <beam number="1">continue</beam>
        <beam number="2">begin</beam>
        </note>
      <note default-x="337.52" default-y="-45.00" dynamics="111.11">
        <pitch>
          <step>D</step>
          <octave>4</octave>
          </pitch>
        <duration>3</duration>
        <voice>2</voice>
        <type>16th</type>
        <accidental>natural</accidental>
        <stem>down</stem>
        <beam number="1">continue</beam>
        <beam number="2">continue</beam>
        </note>
      <note default-x="357.82" default-y="-55.00" dynamics="111.11">
        <pitch>
          <step>B</step>
          <alter>-1</alter>
          <octave>3</octave>
          </pitch>
        <duration>3</duration>
        <voice>2</voice>
        <type>16th</type>
        <stem>down</stem>
        <beam number="1">continue</beam>
        <beam number="2">continue</beam>
        </note>
      <note default-x="386.85" default-y="-50.00" dynamics="111.11">
        <pitch>
          <step>C</step>
          <octave>4</octave>
          </pitch>
        <duration>3</duration>
        <voice>2</voice>
        <type>16th</type>
        <accidental>natural</accidental>
        <stem>down</stem>
        <beam number="1">continue</beam>
        <beam number="2">end</beam>
        </note>
      <note default-x="407.15" default-y="-40.00" dynamics="111.11">
        <pitch>
          <step>E</step>
          <alter>-1</alter>
          <octave>4</octave>
          </pitch>
        <duration>6</duration>
        <voice>2</voice>
        <type>eighth</type>
        <stem>down</stem>
        <beam number="1">end</beam>
        </note>
      <note default-x="451.73" default-y="5.00" dynamics="111.11">
        <pitch>
          <step>B</step>
          <alter>-1</alter>
          <octave>3</octave>
          </pitch>
        <duration>8</duration>
        <voice>2</voice>
        <type>quarter</type>
        <time-modification>
          <actual-notes>3</actual-notes>
          <normal-notes>2</normal-notes>
          <normal-type>eighth</normal-type>
          </time-modification>
        <stem>down</stem>
        <notations>
          <tuplet type="start" bracket="yes"/>
          </notations>
        </note>
      <note default-x="489.27" default-y="5.00" dynamics="111.11">
        <pitch>
          <step>B</step>
          <alter>-2</alter>
          <octave>3</octave>
          </pitch>
        <duration>4</duration>
        <voice>2</voice>
        <type>eighth</type>
        <accidental>flat-flat</accidental>
        <time-modification>
          <actual-notes>3</actual-notes>
          <normal-notes>2</normal-notes>
          <normal-type>eighth</normal-type>
          </time-modification>
        <stem>down</stem>
        <notations>
          <tuplet type="stop"/>
          </notations>
        </note>
      <note default-x="516.29" default-y="-5.00" dynamics="111.11">
        <pitch>
          <step>G</step>
          <octave>3</octave>
          </pitch>
        <duration>12</duration>
        <voice>2</voice>
        <type>quarter</type>
        <accidental>natural</accidental>
        <stem>down</stem>
        </note>
      <note default-x="560.95" default-y="5.00" dynamics="111.11">
        <pitch>
          <step>B</step>
          <alter>-2</alter>
          <octave>3</octave>
          </pitch>
        <duration>6</duration>
        <voice>2</voice>
        <type>eighth</type>
        <stem>down</stem>
        <beam number="1">begin</beam>
        </note>
      <note default-x="593.43" default-y="-5.00" dynamics="111.11">
        <pitch>
          <step>G</step>
          <octave>3</octave>
          </pitch>
        <duration>6</duration>
        <voice>2</voice>
        <type>eighth</type>
        <stem>down</stem>
        <beam number="1">continue</beam>
        </note>
      <note default-x="625.91" default-y="5.00" dynamics="111.11">
        <pitch>
          <step>B</step>
          <alter>-2</alter>
          <octave>3</octave>
          </pitch>
        <duration>4</duration>
        <voice>2</voice>
        <type>eighth</type>
        <time-modification>
          <actual-notes>3</actual-notes>
          <normal-notes>2</normal-notes>
          </time-modification>
        <stem>down</stem>
        <beam number="1">continue</beam>
        <notations>
          <tuplet type="start" bracket="no"/>
          </notations>
        </note>
      <note default-x="682.49" default-y="-45.00" dynamics="111.11">
        <pitch>
          <step>D</step>
          <alter>-1</alter>
          <octave>4</octave>
          </pitch>
        <duration>4</duration>
        <voice>2</voice>
        <type>eighth</type>
        <accidental>flat</accidental>
        <time-modification>
          <actual-notes>3</actual-notes>
          <normal-notes>2</normal-notes>
          </time-modification>
        <stem>down</stem>
        <beam number="1">continue</beam>
        </note>
      <note default-x="707.84" default-y="-40.00" dynamics="111.11">
        <pitch>
          <step>E</step>
          <alter>-1</alter>
          <octave>4</octave>
          </pitch>
        <duration>4</duration>
        <voice>2</voice>
        <type>eighth</type>
        <time-modification>
          <actual-notes>3</actual-notes>
          <normal-notes>2</normal-notes>
          </time-modification>
        <stem>down</stem>
        <beam number="1">end</beam>
        <notations>
          <tuplet type="stop"/>
          </notations>
        </note>
      </measure>
    <measure number="6" width="342.37">
      <note default-x="12.00" default-y="-30.00" dynamics="111.11">
        <pitch>
          <step>G</step>
          <alter>-1</alter>
          <octave>4</octave>
          </pitch>
        <duration>4</duration>
        <voice>1</voice>
        <type>eighth</type>
        <time-modification>
          <actual-notes>3</actual-notes>
          <normal-notes>2</normal-notes>
          </time-modification>
        <stem>down</stem>
        <beam number="1">begin</beam>
        <notations>
          <tuplet type="start" bracket="no"/>
          </notations>
        </note>
      <note default-x="39.02" default-y="-30.00" dynamics="111.11">
        <pitch>
          <step>G</step>
          <octave>4</octave>
          </pitch>
        <duration>4</duration>
        <voice>1</voice>
        <type>eighth</type>
        <accidental>natural</accidental>
        <time-modification>
          <actual-notes>3</actual-notes>
          <normal-notes>2</normal-notes>
          </time-modification>
        <stem>down</stem>
        <beam number="1">continue</beam>
        </note>
      <note default-x="62.39" default-y="-15.00" dynamics="111.11">
        <pitch>
          <step>C</step>
          <alter>-1</alter>
          <octave>5</octave>
          </pitch>
        <duration>4</duration>
        <voice>1</voice>
        <type>eighth</type>
        <time-modification>
          <actual-notes>3</actual-notes>
          <normal-notes>2</normal-notes>
          </time-modification>
        <stem>down</stem>
        <beam number="1">continue</beam>
        <notations>
          <tuplet type="stop"/>
          </notations>
        </note>
      <note default-x="85.76" default-y="-10.00" dynamics="111.11">
        <pitch>
          <step>D</step>
          <alter>-1</alter>
          <octave>5</octave>
          </pitch>
        <duration>4</duration>
        <voice>1</voice>
        <type>eighth</type>
        <time-modification>
          <actual-notes>3</actual-notes>
          <normal-notes>2</normal-notes>
          </time-modification>
        <stem>down</stem>
        <beam number="1">continue</beam>
        <notations>
          <tuplet type="start" bracket="no"/>
          </notations>
        </note>
      <note default-x="109.13" default-y="0.00" dynamics="111.11">
        <pitch>
          <step>F</step>
          <octave>5</octave>
          </pitch>
        <duration>4</duration>
        <voice>1</voice>
        <type>eighth</type>
        <time-modification>
          <actual-notes>3</actual-notes>
          <normal-notes>2</normal-notes>
          </time-modification>
        <stem>down</stem>
        <beam number="1">continue</beam>
        </note>
      <note default-x="136.16" default-y="5.00" dynamics="111.11">
        <pitch>
          <step>G</step>
          <octave>5</octave>
          </pitch>
        <duration>4</duration>
        <tie type="start"/>
        <voice>1</voice>
        <type>eighth</type>
        <accidental>natural</accidental>
        <time-modification>
          <actual-notes>3</actual-notes>
          <normal-notes>2</normal-notes>
          </time-modification>
        <stem>down</stem>
        <beam number="1">end</beam>
        <notations>
          <tied type="start"/>
          <tuplet type="stop"/>
          </notations>
        </note>
      <note default-x="159.53" default-y="5.00" dynamics="111.11">
        <pitch>
          <step>G</step>
          <octave>5</octave>
          </pitch>
        <duration>12</duration>
        <tie type="stop"/>
        <voice>1</voice>
        <type>quarter</type>
        <stem>down</stem>
        <notations>
          <tied type="stop"/>
          </notations>
        </note>
      <note>
        <rest/>
        <duration>36</duration>
        <voice>1</voice>
        <type>half</type>
        <dot/>
        </note>
      <note>
        <rest/>
        <duration>36</duration>
        <voice>1</voice>
        <type>half</type>
        <dot/>
        </note>
      </measure>
    </part>
  </score-partwise>
